KratosMultiphysics/DEMApplication/Chung_Ooi_class.py
KratosMultiphysics/DEMApplication/DEM_analysis_stage.py
KratosMultiphysics/DEMApplication/DEM_benchmarks_class.py
KratosMultiphysics/DEMApplication/DEM_inlet_process.py
KratosMultiphysics/DEMApplication/DEM_material_test_script.py
KratosMultiphysics/DEMApplication/DEM_material_test_script_mpi.py
KratosMultiphysics/DEMApplication/DEM_procedures.py
KratosMultiphysics/DEMApplication/DEM_procedures_mpi.py
KratosMultiphysics/DEMApplication/DEM_procedures_mpi_no_partitions.py
KratosMultiphysics/DEMApplication/DEM_properties_measure_utility.py
KratosMultiphysics/DEMApplication/DEM_restart_utility.py
KratosMultiphysics/DEMApplication/DEM_save_restart_process.py
KratosMultiphysics/DEMApplication/KratosDEM.py
KratosMultiphysics/DEMApplication/KratosDEMAnalysis.py
KratosMultiphysics/DEMApplication/MPIer.py
KratosMultiphysics/DEMApplication/__init__.py
KratosMultiphysics/DEMApplication/angle_finder.py
KratosMultiphysics/DEMApplication/automatic_dt_process.py
KratosMultiphysics/DEMApplication/cartesian_specimen_mdpa_creator.py
KratosMultiphysics/DEMApplication/cluster_file_reader.py
KratosMultiphysics/DEMApplication/concentric_element_size_coarsener.py
KratosMultiphysics/DEMApplication/continuum_sphere_strategy.py
KratosMultiphysics/DEMApplication/control_module_2d_process.py
KratosMultiphysics/DEMApplication/dem_default_input_parameters.py
KratosMultiphysics/DEMApplication/dem_vtk_output.py
KratosMultiphysics/DEMApplication/ice_continuum_sphere_strategy.py
KratosMultiphysics/DEMApplication/materials_assignation_utility.py
KratosMultiphysics/DEMApplication/mesh_creator_cluster.py
KratosMultiphysics/DEMApplication/mesh_creator_sphere.py
KratosMultiphysics/DEMApplication/mesh_to_mdpa_converter.py
KratosMultiphysics/DEMApplication/multiaxial_control_module_generalized_2d_utility.py
KratosMultiphysics/DEMApplication/plot_variables.py
KratosMultiphysics/DEMApplication/sphere_strategy.py
kratosdemapplication-10.4.0.dist-info/METADATA
kratosdemapplication-10.4.0.dist-info/WHEEL
kratosdemapplication-10.4.0.dist-info/RECORD
