Metadata-Version: 2.4
Name: KratosDEMApplication
Version: 10.4.0
Summary:         KRATOS Multiphysics ("Kratos") is a framework for building parallel,         multi-disciplinary simulation software, aiming at modularity,         extensibility, and high performance. Kratos is written in C++,         and counts with an extensive Python interface.     
Author-email: Kratos Team <kratos@listas.cimne.upc.edu>
License: BSD-4-Clause
Classifier: Programming Language :: C++
Classifier: Programming Language :: Python :: 3
Classifier: Topic :: Scientific/Engineering
Requires-Python: >=3.8
Requires-Dist: kratosmultiphysics==10.4.0
